alpha_test_abc_ti_client/__init__.py
alpha_test_abc_ti_client/api_client.py
alpha_test_abc_ti_client/api_response.py
alpha_test_abc_ti_client/configuration.py
alpha_test_abc_ti_client/exceptions.py
alpha_test_abc_ti_client/py.typed
alpha_test_abc_ti_client/rest.py
alpha_test_abc_ti_client/api/__init__.py
alpha_test_abc_ti_client/api/pet_api.py
alpha_test_abc_ti_client/api/store_api.py
alpha_test_abc_ti_client/api/user_api.py
alpha_test_abc_ti_client/models/__init__.py
alpha_test_abc_ti_client/models/address.py
alpha_test_abc_ti_client/models/api_response.py
alpha_test_abc_ti_client/models/category.py
alpha_test_abc_ti_client/models/customer.py
alpha_test_abc_ti_client/models/order.py
alpha_test_abc_ti_client/models/pet.py
alpha_test_abc_ti_client/models/tag.py
alpha_test_abc_ti_client/models/user.py
alpha_test_abc_ti_client-1.0.0.dist-info/METADATA
alpha_test_abc_ti_client-1.0.0.dist-info/WHEEL
alpha_test_abc_ti_client-1.0.0.dist-info/top_level.txt
alpha_test_abc_ti_client-1.0.0.dist-info/RECORD
